GPT2LM/__init__.py
GPT2LM/bigram.py
GPT2LM/bigram_v1.py
GPT2LM/gpt2.py
GPT2LM-0.0.3.dist-info/License
GPT2LM-0.0.3.dist-info/METADATA
GPT2LM-0.0.3.dist-info/WHEEL
GPT2LM-0.0.3.dist-info/top_level.txt
GPT2LM-0.0.3.dist-info/RECORD
