Metadata-Version: 2.1
Name: GPT2LM
Version: 0.0.3
Summary: Implementation of GPT-2 language model for text generation, training custom models and fine-tuning.
Home-page: https://github.com/YashrajBaila7/GPT2LM
Author: Yashraj Baila
Author-email: yashrajbailapython@gmail.com
Keywords: gpt2lm,GPT2LM,gpt,GPT,Language model,Yashraj Baila,AI,Artificial Intelligence,ML,Meachine Learning,Deep Learning,GPT2,gpt2,GPT3,gpt3,GPT4,gpt4,ChatGPT,chatgpt,CHATGPT
Classifier: Programming Language :: Python :: 3
Classifier: License :: OSI Approved :: MIT License
Classifier: Operating System :: OS Independent
Requires-Python: >=3.9
License-File: License
Requires-Dist: yashpyproject
Requires-Dist: torch
Requires-Dist: tqdm
